{
  "945": ["NYC", "Manhattan", "Brooklyn", "Jersey City", "Newark", "Yonkers"],
  "14": ["LA", "Long Beach", "Anaheim", "Santa Ana", "Riverside", "San Bernardino"],
  "634": ["Chicagoland", "Aurora", "Joliet", "Naperville"],
  "140": ["Tacoma", "Bellevue", "Everett"],
  "79": ["Mesa", "Scottsdale", "Chandler", "Tempe", "Gilbert"],
  "7": ["San Jose", "Oakland", "Fremont", "Berkeley"],
  "192": ["Fort Worth", "Arlington", "Plano", "Irving"],
  "247": ["St. Paul", "Bloomington"],
  "233": ["Tampa", "St. Petersburg", "Clearwater"],
  "206": ["Fort Lauderdale", "West Palm Beach", "Boca Raton"],
  "12964": ["Yokohama", "Kawasaki", "Saitama", "Chiba"],
  "12389": ["Incheon", "Suwon", "Seongnam", "Goyang"],
  "12080": ["Shenzhen", "Dongguan", "Foshan", "Zhongshan", "Zhuhai"],
  "12400": ["Suzhou", "Wuxi", "Changzhou", "Nantong"],
  "10687": ["Tianjin", "Langfang", "Baoding"],
  "6955": ["New Delhi", "Noida", "Gurgaon", "Faridabad", "Ghaziabad"],
  "6845": ["Thane", "Navi Mumbai", "Kalyan"],
  "11862": ["Bogor", "Depok", "Tangerang", "Bekasi"],
  "1912": ["Greater London"],
  "2046": ["Ile-de-France"],
  "154": ["Ciudad de Mexico", "CDMX"],
  "2125": ["Ikeja", "Lekki"],
  "3562": ["Constantinople"],
  "2082": ["Randstad", "Den Haag", "The Hague", "Utrecht"],
  "1944": ["Ruhrgebiet", "Ruhr", "Dortmund", "Essen", "Duisburg", "Bochum"],
  "1041": ["Sao Paulo", "Guarulhos", "Campinas"]
}
