[{"h3index": "872db0340ffffff", "population_2015": 57.22331513049557, "total_built_mass_tons": 21480.233487573212, "city_id": 4348, "country_iso": "ISR"}, {"h3index": "872db0344ffffff", "population_2015": 7617.410870518402, "total_built_mass_tons": 2175633.323014747, "city_id": 4348, "country_iso": "ISR"}, {"h3index": "872db0345ffffff", "population_2015": 7002.793856293547, "total_built_mass_tons": 2416555.0223936555, "city_id": 4348, "country_iso": "ISR"}, {"h3index": "872db0346ffffff", "population_2015": 3151.600864298202, "total_built_mass_tons": 584551.1293238301, "city_id": 4348, "country_iso": "ISR"}, {"h3index": "872db0362ffffff", "population_2015": 3372.5757639754056, "total_built_mass_tons": 1073902.5958658326, "city_id": 4348, "country_iso": "ISR"}, {"h3index": "872db0363ffffff", "population_2015": 1497.8351615419576, "total_built_mass_tons": 569926.854233986, "city_id": 4348, "country_iso": "ISR"}, {"h3index": "872db0366ffffff", "population_2015": 680.8903070655524, "total_built_mass_tons": 391746.7371391138, "city_id": 4348, "country_iso": "ISR"}, {"h3index": "872db036affffff", "population_2015": 246.81616769304455, "total_built_mass_tons": 88628.5622545256, "city_id": 4348, "country_iso": "ISR"}, {"h3index": "872db036effffff", "population_2015": 750.7175734314264, "total_built_mass_tons": 172483.46789985348, "city_id": 4348, "country_iso": "ISR"}, {"h3index": "872db0370ffffff", "population_2015": 9640.696648395764, "total_built_mass_tons": 3274840.5128521943, "city_id": 4348, "country_iso": "ISR"}, {"h3index": "872db0371ffffff", "population_2015": 20468.23244077646, "total_built_mass_tons": 5382294.5635885205, "city_id": 4348, "country_iso": "ISR"}, {"h3index": "872db0373ffffff", "population_2015": 1048.1629541284897, "total_built_mass_tons": 179110.57491188584, "city_id": 4348, "country_iso": "ISR"}, {"h3index": "872db0374ffffff", "population_2015": 2130.2355730393347, "total_built_mass_tons": 546220.0547538304, "city_id": 4348, "country_iso": "ISR"}, {"h3index": "872db0375ffffff", "population_2015": 5384.645931969439, "total_built_mass_tons": 1434796.0741763972, "city_id": 4348, "country_iso": "ISR"}, {"h3index": "872db0376ffffff", "population_2015": 642.9218923306933, "total_built_mass_tons": 372483.05137203936, "city_id": 4348, "country_iso": "ISR"}, {"h3index": "872db0ad9ffffff", "population_2015": 14.656102520811793, "total_built_mass_tons": 4268.221263513048, "city_id": 4348, "country_iso": "ISR"}, {"h3index": "872db0adbffffff", "population_2015": 633.4891134187288, "total_built_mass_tons": 413345.17914800986, "city_id": 4348, "country_iso": "ISR"}]