[{"h3index": "8741ae00affffff", "population_2015": 10870.539010981018, "total_built_mass_tons": 2507099.4798769956, "city_id": 12331, "country_iso": "CHN"}, {"h3index": "8741ae00bffffff", "population_2015": 14271.525806087606, "total_built_mass_tons": 3583107.6048486196, "city_id": 12331, "country_iso": "CHN"}, {"h3index": "8741ae018ffffff", "population_2015": 814.3288266574635, "total_built_mass_tons": 353515.12202521984, "city_id": 12331, "country_iso": "CHN"}, {"h3index": "8741ae019ffffff", "population_2015": 7655.028365815387, "total_built_mass_tons": 2158652.6981247915, "city_id": 12331, "country_iso": "CHN"}, {"h3index": "8741ae01affffff", "population_2015": 131.23065928010377, "total_built_mass_tons": 110279.48022556864, "city_id": 12331, "country_iso": "CHN"}, {"h3index": "8741ae01bffffff", "population_2015": 1374.4510730425516, "total_built_mass_tons": 734909.5951544233, "city_id": 12331, "country_iso": "CHN"}, {"h3index": "8741ae0e4ffffff", "population_2015": 16848.816386761384, "total_built_mass_tons": 5672264.145495974, "city_id": 12331, "country_iso": "CHN"}, {"h3index": "8741ae0e5ffffff", "population_2015": 4013.433722282858, "total_built_mass_tons": 751770.794939672, "city_id": 12331, "country_iso": "CHN"}, {"h3index": "8741ae0e6ffffff", "population_2015": 2369.00614602893, "total_built_mass_tons": 909212.2197504096, "city_id": 12331, "country_iso": "CHN"}, {"h3index": "8741ae0f4ffffff", "population_2015": 15.312045252556894, "total_built_mass_tons": 13598.081471158175, "city_id": 12331, "country_iso": "CHN"}]