[{"h3index": "8710c2280ffffff", "population_2015": 2826.2410891233694, "total_built_mass_tons": 1070515.227666661, "city_id": 5489, "country_iso": "RUS"}, {"h3index": "8710c2281ffffff", "population_2015": 22907.022292094138, "total_built_mass_tons": 6614620.129137438, "city_id": 5489, "country_iso": "RUS"}, {"h3index": "8710c2282ffffff", "population_2015": 404.8310525739894, "total_built_mass_tons": 346245.72422028455, "city_id": 5489, "country_iso": "RUS"}, {"h3index": "8710c2283ffffff", "population_2015": 9942.333622526656, "total_built_mass_tons": 4385873.1398751605, "city_id": 5489, "country_iso": "RUS"}, {"h3index": "8710c2284ffffff", "population_2015": 2.5319776759428136, "total_built_mass_tons": 1553.5553371094256, "city_id": 5489, "country_iso": "RUS"}, {"h3index": "8710c2285ffffff", "population_2015": 4946.970402680191, "total_built_mass_tons": 1875702.629757564, "city_id": 5489, "country_iso": "RUS"}, {"h3index": "8710c2288ffffff", "population_2015": 27084.107022689383, "total_built_mass_tons": 8793647.849297369, "city_id": 5489, "country_iso": "RUS"}, {"h3index": "8710c2289ffffff", "population_2015": 32628.961489165067, "total_built_mass_tons": 8413002.184772141, "city_id": 5489, "country_iso": "RUS"}, {"h3index": "8710c228affffff", "population_2015": 22347.47714692472, "total_built_mass_tons": 7102699.041484227, "city_id": 5489, "country_iso": "RUS"}, {"h3index": "8710c228bffffff", "population_2015": 25733.274191329052, "total_built_mass_tons": 8249270.235296452, "city_id": 5489, "country_iso": "RUS"}, {"h3index": "8710c228cffffff", "population_2015": 3850.5981269181943, "total_built_mass_tons": 932143.9165210484, "city_id": 5489, "country_iso": "RUS"}, {"h3index": "8710c228dffffff", "population_2015": 13636.575816046025, "total_built_mass_tons": 4037032.721480239, "city_id": 5489, "country_iso": "RUS"}, {"h3index": "8710c228effffff", "population_2015": 22864.56083735297, "total_built_mass_tons": 7486678.299329363, "city_id": 5489, "country_iso": "RUS"}, {"h3index": "8710c2290ffffff", "population_2015": 90.65754367977964, "total_built_mass_tons": 100537.44339306442, "city_id": 5489, "country_iso": "RUS"}, {"h3index": "8710c2291ffffff", "population_2015": 3064.2815206191112, "total_built_mass_tons": 1280443.774838522, "city_id": 5489, "country_iso": "RUS"}, {"h3index": "8710c2292ffffff", "population_2015": 1996.0418795333187, "total_built_mass_tons": 1333557.9177400435, "city_id": 5489, "country_iso": "RUS"}, {"h3index": "8710c2293ffffff", "population_2015": 6143.4117396392085, "total_built_mass_tons": 2998400.3510364336, "city_id": 5489, "country_iso": "RUS"}, {"h3index": "8710c2298ffffff", "population_2015": 31925.03417300805, "total_built_mass_tons": 8753942.680952359, "city_id": 5489, "country_iso": "RUS"}, {"h3index": "8710c2299ffffff", "population_2015": 27936.98582173516, "total_built_mass_tons": 10064515.67724164, "city_id": 5489, "country_iso": "RUS"}, {"h3index": "8710c229affffff", "population_2015": 21841.610821959555, "total_built_mass_tons": 6190487.2595223, "city_id": 5489, "country_iso": "RUS"}, {"h3index": "8710c229bffffff", "population_2015": 31554.69690757453, "total_built_mass_tons": 9782610.248597264, "city_id": 5489, "country_iso": "RUS"}, {"h3index": "8710c229cffffff", "population_2015": 5995.580623629514, "total_built_mass_tons": 2217784.7599738035, "city_id": 5489, "country_iso": "RUS"}, {"h3index": "8710c229dffffff", "population_2015": 25117.15311371485, "total_built_mass_tons": 7640271.804441982, "city_id": 5489, "country_iso": "RUS"}, {"h3index": "8710c229effffff", "population_2015": 14881.96075629814, "total_built_mass_tons": 4038681.9633882623, "city_id": 5489, "country_iso": "RUS"}, {"h3index": "8710c22aaffffff", "population_2015": 634.2879972027797, "total_built_mass_tons": 592640.6774692589, "city_id": 5489, "country_iso": "RUS"}, {"h3index": "8710c22d2ffffff", "population_2015": 2922.2906575137504, "total_built_mass_tons": 1066043.2993412656, "city_id": 5489, "country_iso": "RUS"}, {"h3index": "8710c22d3ffffff", "population_2015": 1992.3861739158629, "total_built_mass_tons": 1871029.615867761, "city_id": 5489, "country_iso": "RUS"}, {"h3index": "8710c22d4ffffff", "population_2015": 515.2674605743557, "total_built_mass_tons": 355825.494855799, "city_id": 5489, "country_iso": "RUS"}, {"h3index": "8710c22d6ffffff", "population_2015": 8154.274374066149, "total_built_mass_tons": 2421462.2173058963, "city_id": 5489, "country_iso": "RUS"}, {"h3index": "8710c22deffffff", "population_2015": 11.507682859196382, "total_built_mass_tons": 13323.933128406774, "city_id": 5489, "country_iso": "RUS"}, {"h3index": "8710c22f0ffffff", "population_2015": 1077.9430020472582, "total_built_mass_tons": 490466.0992714653, "city_id": 5489, "country_iso": "RUS"}, {"h3index": "8710c22f2ffffff", "population_2015": 4902.018969157164, "total_built_mass_tons": 1734793.1850995547, "city_id": 5489, "country_iso": "RUS"}, {"h3index": "8710c22f3ffffff", "population_2015": 71.33734753178616, "total_built_mass_tons": 70587.67377762772, "city_id": 5489, "country_iso": "RUS"}, {"h3index": "8710c22f6ffffff", "population_2015": 96.57428085710488, "total_built_mass_tons": 65880.1102185325, "city_id": 5489, "country_iso": "RUS"}, {"h3index": "8710c2648ffffff", "population_2015": 1265.4708918449928, "total_built_mass_tons": 603393.112622878, "city_id": 5489, "country_iso": "RUS"}, {"h3index": "8710c2649ffffff", "population_2015": 7.751209341310988, "total_built_mass_tons": 8660.082075866707, "city_id": 5489, "country_iso": "RUS"}, {"h3index": "8710c264cffffff", "population_2015": 173.4727610288882, "total_built_mass_tons": 97397.2464380714, "city_id": 5489, "country_iso": "RUS"}, {"h3index": "8710c264dffffff", "population_2015": 14095.321850580329, "total_built_mass_tons": 5297867.246134502, "city_id": 5489, "country_iso": "RUS"}, {"h3index": "8710c264effffff", "population_2015": 363.9311283812803, "total_built_mass_tons": 314169.49277487415, "city_id": 5489, "country_iso": "RUS"}, {"h3index": "8710c2665ffffff", "population_2015": 19.904485814711627, "total_built_mass_tons": 10319.01053146948, "city_id": 5489, "country_iso": "RUS"}, {"h3index": "8710c2668ffffff", "population_2015": 4780.689297605963, "total_built_mass_tons": 2058787.8229090392, "city_id": 5489, "country_iso": "RUS"}, {"h3index": "8710c2669ffffff", "population_2015": 7258.030596595654, "total_built_mass_tons": 3034810.8259705636, "city_id": 5489, "country_iso": "RUS"}, {"h3index": "8710c266affffff", "population_2015": 483.9978603026447, "total_built_mass_tons": 282457.6192217672, "city_id": 5489, "country_iso": "RUS"}, {"h3index": "8710c266bffffff", "population_2015": 12303.389013979478, "total_built_mass_tons": 4249375.647052805, "city_id": 5489, "country_iso": "RUS"}, {"h3index": "8710c266cffffff", "population_2015": 745.6344299325757, "total_built_mass_tons": 423911.6187520182, "city_id": 5489, "country_iso": "RUS"}, {"h3index": "8710c266dffffff", "population_2015": 7140.70157325969, "total_built_mass_tons": 3871119.00894685, "city_id": 5489, "country_iso": "RUS"}, {"h3index": "8710c266effffff", "population_2015": 7.624070185306025, "total_built_mass_tons": 6434.9106326838955, "city_id": 5489, "country_iso": "RUS"}, {"h3index": "8710dc904ffffff", "population_2015": 2647.579731447556, "total_built_mass_tons": 943282.4692822476, "city_id": 5489, "country_iso": "RUS"}, {"h3index": "8710dc914ffffff", "population_2015": 34.97701558505788, "total_built_mass_tons": 25185.038635796333, "city_id": 5489, "country_iso": "RUS"}, {"h3index": "8710dc920ffffff", "population_2015": 19769.27969333892, "total_built_mass_tons": 6312858.592072457, "city_id": 5489, "country_iso": "RUS"}, {"h3index": "8710dc921ffffff", "population_2015": 91.25263593804604, "total_built_mass_tons": 95451.11306785468, "city_id": 5489, "country_iso": "RUS"}, {"h3index": "8710dc922ffffff", "population_2015": 22824.81361460031, "total_built_mass_tons": 5949120.470907074, "city_id": 5489, "country_iso": "RUS"}, {"h3index": "8710dc923ffffff", "population_2015": 10696.10635204689, "total_built_mass_tons": 3304056.145884366, "city_id": 5489, "country_iso": "RUS"}, {"h3index": "8710dc924ffffff", "population_2015": 29317.81117556331, "total_built_mass_tons": 8275515.400844333, "city_id": 5489, "country_iso": "RUS"}, {"h3index": "8710dc925ffffff", "population_2015": 18539.72798546437, "total_built_mass_tons": 5690392.983711063, "city_id": 5489, "country_iso": "RUS"}, {"h3index": "8710dc926ffffff", "population_2015": 33324.564104921694, "total_built_mass_tons": 11278231.88612589, "city_id": 5489, "country_iso": "RUS"}, {"h3index": "8710dc928ffffff", "population_2015": 312.14406487661245, "total_built_mass_tons": 221534.2653496371, "city_id": 5489, "country_iso": "RUS"}, {"h3index": "8710dc92cffffff", "population_2015": 3329.116387001673, "total_built_mass_tons": 1413593.201988488, "city_id": 5489, "country_iso": "RUS"}, {"h3index": "8710dc92effffff", "population_2015": 94.65580426384422, "total_built_mass_tons": 88920.41191044632, "city_id": 5489, "country_iso": "RUS"}, {"h3index": "8710dc930ffffff", "population_2015": 19883.39180937, "total_built_mass_tons": 6702795.100670274, "city_id": 5489, "country_iso": "RUS"}, {"h3index": "8710dc931ffffff", "population_2015": 293.4321738205704, "total_built_mass_tons": 136547.3590491934, "city_id": 5489, "country_iso": "RUS"}, {"h3index": "8710dc932ffffff", "population_2015": 5711.013762590932, "total_built_mass_tons": 2203575.895679941, "city_id": 5489, "country_iso": "RUS"}, {"h3index": "8710dc933ffffff", "population_2015": 6972.651837001126, "total_built_mass_tons": 2493261.4857930103, "city_id": 5489, "country_iso": "RUS"}, {"h3index": "8710dc934ffffff", "population_2015": 23606.965563916223, "total_built_mass_tons": 6763040.329046435, "city_id": 5489, "country_iso": "RUS"}, {"h3index": "8710dc935ffffff", "population_2015": 20558.80273799149, "total_built_mass_tons": 6611502.945713424, "city_id": 5489, "country_iso": "RUS"}, {"h3index": "8710dc936ffffff", "population_2015": 23813.041955940393, "total_built_mass_tons": 7761476.683877904, "city_id": 5489, "country_iso": "RUS"}]