[{"h3index": "874cd5104ffffff", "population_2015": 702.1590995788574, "total_built_mass_tons": 77664.1757300344, "city_id": 830, "country_iso": "DOM"}, {"h3index": "874cd5105ffffff", "population_2015": 3463.1830892675066, "total_built_mass_tons": 399388.83941061166, "city_id": 830, "country_iso": "DOM"}, {"h3index": "874cd5120ffffff", "population_2015": 13889.40847628724, "total_built_mass_tons": 1316558.7939960554, "city_id": 830, "country_iso": "DOM"}, {"h3index": "874cd5121ffffff", "population_2015": 22715.40065775852, "total_built_mass_tons": 2870851.8585472964, "city_id": 830, "country_iso": "DOM"}, {"h3index": "874cd5122ffffff", "population_2015": 2935.025629400739, "total_built_mass_tons": 288959.0586817415, "city_id": 830, "country_iso": "DOM"}, {"h3index": "874cd5123ffffff", "population_2015": 19265.177325693763, "total_built_mass_tons": 2621763.9169171276, "city_id": 830, "country_iso": "DOM"}, {"h3index": "874cd5124ffffff", "population_2015": 854.5413556790819, "total_built_mass_tons": 78720.87056683296, "city_id": 830, "country_iso": "DOM"}, {"h3index": "874cd5125ffffff", "population_2015": 7983.809062351899, "total_built_mass_tons": 896461.4817623666, "city_id": 830, "country_iso": "DOM"}, {"h3index": "874cd5126ffffff", "population_2015": 280.26839452257343, "total_built_mass_tons": 27485.425110551983, "city_id": 830, "country_iso": "DOM"}, {"h3index": "874cd5128ffffff", "population_2015": 130.25539676067876, "total_built_mass_tons": 17475.841421038676, "city_id": 830, "country_iso": "DOM"}, {"h3index": "874cd512affffff", "population_2015": 322.3851495780196, "total_built_mass_tons": 34176.12439547261, "city_id": 830, "country_iso": "DOM"}, {"h3index": "874cd512cffffff", "population_2015": 916.523127522188, "total_built_mass_tons": 128622.338939745, "city_id": 830, "country_iso": "DOM"}, {"h3index": "874cd512effffff", "population_2015": 13766.04958276188, "total_built_mass_tons": 1560151.5889816217, "city_id": 830, "country_iso": "DOM"}, {"h3index": "874cd58d2ffffff", "population_2015": 8706.903591589835, "total_built_mass_tons": 1014247.0802421782, "city_id": 830, "country_iso": "DOM"}, {"h3index": "874cd58d6ffffff", "population_2015": 666.8339745914236, "total_built_mass_tons": 48119.54839690149, "city_id": 830, "country_iso": "DOM"}]